README.md
setup.py
r2dto/__init__.py
r2dto/base.py
r2dto/fields.py
r2dto/validators.py
r2dto.egg-info/PKG-INFO
r2dto.egg-info/SOURCES.txt
r2dto.egg-info/dependency_links.txt
r2dto.egg-info/top_level.txt
tests/__init__.py
tests/__main__.py
tests/test_acceptance.py
tests/test_base_serializer.py