Metadata-Version: 1.1
Name: r2dto
Version: 0.0.6
Summary: Package to convert arbitrary python objects into DTOs ready for serialization and validation.
Home-page: https://github.com/nickswebsite/r2dto
Author: The Magnificant Nick
Author-email: send_me_spam@yahoo.com
License: UNKNOWN
Keywords: dto serializer serialize REST marshal JSON
Platform: UNKNOWN
Classifier: Development Status :: 3 - Alpha
Classifier: Intended Audience :: Developers
Classifier: License :: Public Domain
Classifier: Programming Language :: Python
Classifier: Topic :: Internet :: WWW/HTTP :: Dynamic Content
Classifier: Topic :: Internet :: WWW/HTTP :: Dynamic Content :: CGI Tools/Libraries
Classifier: Topic :: Software Development
